{
  "attendance": "3450",
  "date": "2025.10.19",
  "venueRaw": "Venue: Kami Arena",
  "leagueType": "B1",
  "round": "ROUND4",
  "venue": "Kami Arena",
  "homeName": "島根スサノオマジック",
  "awayName": "横浜ビー・コルセアーズ",
  "home": {
    "total": {
      "pts": 101,
      "f2m": 31,
      "f2a": 41,
      "f3m": 8,
      "f3a": 23,
      "ftm": 15,
      "fta": 20,
      "oreb": 13,
      "dreb": 26,
      "reb": 39,
      "ast": 28,
      "tov": 12,
      "stl": 6,
      "blk": 0,
      "pf": 15
    },
    "starters": [
      {
        "no": "4",
        "nameJp": "ニック・ケイ",
        "min": "31:10",
        "pts": 22,
        "f2m": 10,
        "f2a": 12,
        "f3m": 0,
        "f3a": 3,
        "ftm": 2,
        "fta": 5,
        "oreb": 5,
        "dreb": 1,
        "reb": 6,
        "ast": 6,
        "tov": 1,
        "stl": 1,
        "blk": 0,
        "pf": 0,
        "isStarter": true,
        "detailUrl": "https://www.bleague.jp/roster_detail/?PlayerID=5100000088",
        "name": "Nick Kay"
      },
      {
        "no": "6",
        "nameJp": "北川 弘",
        "min": "20:12",
        "pts": 4,
        "f2m": 2,
        "f2a": 2,
        "f3m": 0,
        "f3a": 2,
        "ftm": 0,
        "fta": 0,
        "oreb": 0,
        "dreb": 1,
        "reb": 1,
        "ast": 1,
        "tov": 0,
        "stl": 0,
        "blk": 0,
        "pf": 5,
        "isStarter": true,
        "detailUrl": "https://www.bleague.jp/roster_detail/?PlayerID=8532",
        "name": "Hiromu Kitagawa"
      },
      {
        "no": "14",
        "nameJp": "ジェームズ・マイケル・マカドゥ",
        "min": "23:50",
        "pts": 15,
        "f2m": 7,
        "f2a": 10,
        "f3m": 0,
        "f3a": 0,
        "ftm": 1,
        "fta": 3,
        "oreb": 2,
        "dreb": 12,
        "reb": 14,
        "ast": 2,
        "tov": 0,
        "stl": 1,
        "blk": 0,
        "pf": 2,
        "isStarter": true,
        "detailUrl": "https://www.bleague.jp/roster_detail/?PlayerID=32992",
        "name": "James Michael Mcadoo"
      },
      {
        "no": "22",
        "nameJp": "飯尾 文哉",
        "min": "30:09",
        "pts": 7,
        "f2m": 2,
        "f2a": 2,
        "f3m": 1,
        "f3a": 2,
        "ftm": 0,
        "fta": 0,
        "oreb": 0,
        "dreb": 0,
        "reb": 0,
        "ast": 1,
        "tov": 4,
        "stl": 1,
        "blk": 0,
        "pf": 2,
        "isStarter": true,
        "detailUrl": "https://www.bleague.jp/roster_detail/?PlayerID=51000113",
        "name": "Fumiya Iio"
      },
      {
        "no": "77",
        "nameJp": "岡田 侑大",
        "min": "30:47",
        "pts": 21,
        "f2m": 4,
        "f2a": 8,
        "f3m": 3,
        "f3a": 6,
        "ftm": 4,
        "fta": 4,
        "oreb": 2,
        "dreb": 5,
        "reb": 7,
        "ast": 5,
        "tov": 1,
        "stl": 0,
        "blk": 0,
        "pf": 2,
        "isStarter": true,
        "detailUrl": "https://www.bleague.jp/roster_detail/?PlayerID=18475",
        "name": "Yuta Okada"
      }
    ]
  },
  "away": {
    "total": {
      "pts": 82,
      "f2m": 17,
      "f2a": 34,
      "f3m": 14,
      "f3a": 33,
      "ftm": 6,
      "fta": 9,
      "oreb": 12,
      "dreb": 16,
      "reb": 28,
      "ast": 18,
      "tov": 11,
      "stl": 6,
      "blk": 0,
      "pf": 24
    },
    "starters": [
      {
        "no": "3",
        "nameJp": "安藤 誓哉",
        "min": "30:14",
        "pts": 22,
        "f2m": 3,
        "f2a": 8,
        "f3m": 4,
        "f3a": 8,
        "ftm": 4,
        "fta": 4,
        "oreb": 1,
        "dreb": 0,
        "reb": 1,
        "ast": 7,
        "tov": 0,
        "stl": 1,
        "blk": 0,
        "pf": 3,
        "isStarter": true,
        "detailUrl": "https://www.bleague.jp/roster_detail/?PlayerID=8467",
        "name": "Seiya Ando"
      },
      {
        "no": "4",
        "nameJp": "ダミアン・イングリス",
        "min": "28:11",
        "pts": 20,
        "f2m": 6,
        "f2a": 12,
        "f3m": 2,
        "f3a": 2,
        "ftm": 2,
        "fta": 3,
        "oreb": 3,
        "dreb": 9,
        "reb": 12,
        "ast": 1,
        "tov": 4,
        "stl": 1,
        "blk": 0,
        "pf": 2,
        "isStarter": true,
        "detailUrl": "https://www.bleague.jp/roster_detail/?PlayerID=51000412",
        "name": "Damien Inglis"
      },
      {
        "no": "8",
        "nameJp": "ゲイリー・クラーク",
        "min": "27:36",
        "pts": 8,
        "f2m": 1,
        "f2a": 2,
        "f3m": 2,
        "f3a": 7,
        "ftm": 0,
        "fta": 0,
        "oreb": 2,
        "dreb": 2,
        "reb": 4,
        "ast": 0,
        "tov": 0,
        "stl": 1,
        "blk": 0,
        "pf": 0,
        "isStarter": true,
        "detailUrl": "https://www.bleague.jp/roster_detail/?PlayerID=51000406",
        "name": "Gary Clark"
      },
      {
        "no": "24",
        "nameJp": "松崎 裕樹",
        "min": "14:21",
        "pts": 2,
        "f2m": 1,
        "f2a": 1,
        "f3m": 0,
        "f3a": 3,
        "ftm": 0,
        "fta": 2,
        "oreb": 2,
        "dreb": 2,
        "reb": 4,
        "ast": 1,
        "tov": 0,
        "stl": 1,
        "blk": 0,
        "pf": 2,
        "isStarter": true,
        "detailUrl": "https://www.bleague.jp/roster_detail/?PlayerID=51000227",
        "name": "Hiroki Matsuzaki"
      },
      {
        "no": "30",
        "nameJp": "須藤 昂矢",
        "min": "18:29",
        "pts": 4,
        "f2m": 2,
        "f2a": 2,
        "f3m": 0,
        "f3a": 0,
        "ftm": 0,
        "fta": 0,
        "oreb": 0,
        "dreb": 0,
        "reb": 0,
        "ast": 0,
        "tov": 1,
        "stl": 0,
        "blk": 0,
        "pf": 2,
        "isStarter": true,
        "detailUrl": "https://www.bleague.jp/roster_detail/?PlayerID=32956",
        "name": "Koya Sudo"
      }
    ]
  }
}