{
  "attendance": "4333",
  "date": "2026.01.04",
  "venueRaw": "Venue: Shiga Daihatsu Arena",
  "leagueType": "B1",
  "round": "ROUND18",
  "venue": "Shiga Daihatsu Arena",
  "homeName": "滋賀レイクス",
  "awayName": "茨城ロボッツ",
  "home": {
    "total": {
      "pts": 61,
      "f2m": 10,
      "f2a": 29,
      "f3m": 11,
      "f3a": 34,
      "ftm": 8,
      "fta": 10,
      "oreb": 7,
      "dreb": 26,
      "reb": 33,
      "ast": 21,
      "tov": 11,
      "stl": 7,
      "blk": 3,
      "pf": 21
    },
    "starters": [
      {
        "no": "0",
        "nameJp": "ザック・オーガスト",
        "min": "36:21",
        "pts": 16,
        "f2m": 5,
        "f2a": 12,
        "f3m": 0,
        "f3a": 5,
        "ftm": 6,
        "fta": 8,
        "oreb": 1,
        "dreb": 13,
        "reb": 14,
        "ast": 3,
        "tov": 4,
        "stl": 2,
        "blk": 2,
        "pf": 2,
        "isStarter": true,
        "detailUrl": "https://www.bleague.jp/roster_detail/?PlayerID=51000312",
        "name": "Zach Auguste"
      },
      {
        "no": "7",
        "nameJp": "游 艾喆",
        "min": "20:18",
        "pts": 5,
        "f2m": 1,
        "f2a": 3,
        "f3m": 1,
        "f3a": 2,
        "ftm": 0,
        "fta": 0,
        "oreb": 1,
        "dreb": 0,
        "reb": 1,
        "ast": 3,
        "tov": 0,
        "stl": 2,
        "blk": 0,
        "pf": 1,
        "isStarter": true,
        "detailUrl": "https://www.bleague.jp/roster_detail/?PlayerID=51000382",
        "name": "Ai-che Yu"
      },
      {
        "no": "17",
        "nameJp": "常田 耕平",
        "min": "17:23",
        "pts": 3,
        "f2m": 0,
        "f2a": 0,
        "f3m": 1,
        "f3a": 2,
        "ftm": 0,
        "fta": 0,
        "oreb": 0,
        "dreb": 1,
        "reb": 1,
        "ast": 0,
        "tov": 0,
        "stl": 0,
        "blk": 0,
        "pf": 2,
        "isStarter": true,
        "detailUrl": "https://www.bleague.jp/roster_detail/?PlayerID=5100000040",
        "name": "Kohei Tsuneta"
      },
      {
        "no": "20",
        "nameJp": "トーマス・ウィンブッシュ",
        "min": "16:01",
        "pts": 4,
        "f2m": 2,
        "f2a": 4,
        "f3m": 0,
        "f3a": 3,
        "ftm": 0,
        "fta": 0,
        "oreb": 1,
        "dreb": 2,
        "reb": 3,
        "ast": 1,
        "tov": 1,
        "stl": 0,
        "blk": 1,
        "pf": 3,
        "isStarter": true,
        "detailUrl": "https://www.bleague.jp/roster_detail/?PlayerID=51000292",
        "name": "Thomas Wimbush"
      },
      {
        "no": "25",
        "nameJp": "江原 信太朗",
        "min": "20:41",
        "pts": 3,
        "f2m": 0,
        "f2a": 0,
        "f3m": 1,
        "f3a": 5,
        "ftm": 0,
        "fta": 0,
        "oreb": 1,
        "dreb": 2,
        "reb": 3,
        "ast": 0,
        "tov": 0,
        "stl": 0,
        "blk": 0,
        "pf": 0,
        "isStarter": true,
        "detailUrl": "https://www.bleague.jp/roster_detail/?PlayerID=51000343",
        "name": "Shintaro Ehara"
      }
    ]
  },
  "away": {
    "total": {
      "pts": 88,
      "f2m": 23,
      "f2a": 42,
      "f3m": 9,
      "f3a": 25,
      "ftm": 15,
      "fta": 22,
      "oreb": 12,
      "dreb": 36,
      "reb": 48,
      "ast": 24,
      "tov": 8,
      "stl": 4,
      "blk": 2,
      "pf": 15
    },
    "starters": [
      {
        "no": "0",
        "nameJp": "ロバート・フランクス",
        "min": "29:19",
        "pts": 17,
        "f2m": 4,
        "f2a": 7,
        "f3m": 2,
        "f3a": 3,
        "ftm": 3,
        "fta": 4,
        "oreb": 1,
        "dreb": 8,
        "reb": 9,
        "ast": 1,
        "tov": 4,
        "stl": 0,
        "blk": 1,
        "pf": 1,
        "isStarter": true,
        "detailUrl": "https://www.bleague.jp/roster_detail/?PlayerID=51000277",
        "name": "Robert Franks"
      },
      {
        "no": "3",
        "nameJp": "長谷川 暢",
        "min": "21:34",
        "pts": 16,
        "f2m": 3,
        "f2a": 6,
        "f3m": 3,
        "f3a": 4,
        "ftm": 1,
        "fta": 1,
        "oreb": 1,
        "dreb": 1,
        "reb": 2,
        "ast": 7,
        "tov": 2,
        "stl": 3,
        "blk": 0,
        "pf": 2,
        "isStarter": true,
        "detailUrl": "https://www.bleague.jp/roster_detail/?PlayerID=15829",
        "name": "Noboru Hasegawa"
      },
      {
        "no": "7",
        "nameJp": "駒沢 颯",
        "min": "21:06",
        "pts": 3,
        "f2m": 0,
        "f2a": 2,
        "f3m": 1,
        "f3a": 4,
        "ftm": 0,
        "fta": 0,
        "oreb": 0,
        "dreb": 1,
        "reb": 1,
        "ast": 2,
        "tov": 1,
        "stl": 0,
        "blk": 0,
        "pf": 3,
        "isStarter": true,
        "detailUrl": "https://www.bleague.jp/roster_detail/?PlayerID=5100000032",
        "name": "Hayate Komasawa"
      },
      {
        "no": "10",
        "nameJp": "陳岡 流羽",
        "min": "22:57",
        "pts": 7,
        "f2m": 1,
        "f2a": 2,
        "f3m": 1,
        "f3a": 5,
        "ftm": 2,
        "fta": 3,
        "oreb": 0,
        "dreb": 2,
        "reb": 2,
        "ast": 1,
        "tov": 0,
        "stl": 0,
        "blk": 0,
        "pf": 3,
        "isStarter": true,
        "detailUrl": "https://www.bleague.jp/roster_detail/?PlayerID=51000479",
        "name": "Ru Jingaoka"
      },
      {
        "no": "21",
        "nameJp": "エリック・ジェイコブセン",
        "min": "23:08",
        "pts": 9,
        "f2m": 3,
        "f2a": 4,
        "f3m": 0,
        "f3a": 1,
        "ftm": 3,
        "fta": 7,
        "oreb": 4,
        "dreb": 8,
        "reb": 12,
        "ast": 1,
        "tov": 1,
        "stl": 0,
        "blk": 1,
        "pf": 1,
        "isStarter": true,
        "detailUrl": "https://www.bleague.jp/roster_detail/?PlayerID=12634",
        "name": "Eric Jacobsen"
      }
    ]
  }
}